CONTRIBUTING.md
LICENSE
MANIFEST.in
README.md
VERSION
setup.cfg
setup.py
docs/Makefile
docs/conf.py
docs/index.rst
docs/make.bat
src/akro/__init__.py
src/akro/box.py
src/akro/dict.py
src/akro/discrete.py
src/akro/image.py
src/akro/requires.py
src/akro/space.py
src/akro/tuple.py
src/akro.egg-info/PKG-INFO
src/akro.egg-info/SOURCES.txt
src/akro.egg-info/dependency_links.txt
src/akro.egg-info/requires.txt
src/akro.egg-info/top_level.txt
tests/__init__.py
tests/akro/__init__.py
tests/akro/test_akro_convert.py
tests/akro/test_box.py
tests/akro/test_dict.py
tests/akro/test_discrete.py
tests/akro/test_image.py
tests/akro/test_tuple.py