Metadata-Version: 2.1
Name: akro
Version: 0.0.8
Summary: Spaces types for reinforcement learning
Home-page: https://github.com/rlworkgroup/akro
Author: Reinforcement Learning Working Group
Author-email: akro@noreply.github.com
License: MIT
Platform: UNKNOWN
Classifier: Development Status :: 4 - Beta
Classifier: Intended Audience :: Developers
Classifier: Intended Audience :: Education
Classifier: Intended Audience :: Science/Research
Classifier: License :: OSI Approved :: MIT License
Classifier: Programming Language :: Python :: 3.5
Classifier: Programming Language :: Python :: 3.6
Classifier: Programming Language :: Python :: 3.7
Classifier: Programming Language :: Python :: 3 :: Only
Classifier: Topic :: Scientific/Engineering :: Artificial Intelligence
Classifier: Topic :: Scientific/Engineering :: Mathematics
Classifier: Topic :: Software Development :: Libraries
Requires-Python: >=3.5
Provides-Extra: dev
Provides-Extra: all
Provides-Extra: tf
Provides-Extra: theano
